ovos_skill_iss_location/LICENSE
ovos_skill_iss_location/MANIFEST.in
ovos_skill_iss_location/README.md
ovos_skill_iss_location/__init__.py
ovos_skill_iss_location/gui-requirements.txt
ovos_skill_iss_location/requirements.txt
ovos_skill_iss_location/version.py
ovos_skill_iss_location/gui/all/iss.png
ovos_skill_iss_location/gui/all/iss2.png
ovos_skill_iss_location/gui/all/iss3.png
ovos_skill_iss_location/locale/ca-es/how_many.voc
ovos_skill_iss_location/locale/ca-es/iss.voc
ovos_skill_iss_location/locale/ca-es/location.current.dialog
ovos_skill_iss_location/locale/ca-es/location.unknown.dialog
ovos_skill_iss_location/locale/ca-es/location.when.dialog
ovos_skill_iss_location/locale/ca-es/number.dialog
ovos_skill_iss_location/locale/ca-es/onboard.voc
ovos_skill_iss_location/locale/ca-es/skill.json
ovos_skill_iss_location/locale/ca-es/visible_for.dialog
ovos_skill_iss_location/locale/ca-es/when_iss.intent
ovos_skill_iss_location/locale/ca-es/where_iss.intent
ovos_skill_iss_location/locale/ca-es/who.dialog
ovos_skill_iss_location/locale/ca-es/who.voc
ovos_skill_iss_location/locale/da-dk/how_many.voc
ovos_skill_iss_location/locale/da-dk/iss.voc
ovos_skill_iss_location/locale/da-dk/location.current.dialog
ovos_skill_iss_location/locale/da-dk/location.unknown.dialog
ovos_skill_iss_location/locale/da-dk/location.when.dialog
ovos_skill_iss_location/locale/da-dk/number.dialog
ovos_skill_iss_location/locale/da-dk/onboard.voc
ovos_skill_iss_location/locale/da-dk/skill.json
ovos_skill_iss_location/locale/da-dk/visible_for.dialog
ovos_skill_iss_location/locale/da-dk/when_iss.intent
ovos_skill_iss_location/locale/da-dk/where_iss.intent
ovos_skill_iss_location/locale/da-dk/who.dialog
ovos_skill_iss_location/locale/da-dk/who.voc
ovos_skill_iss_location/locale/de-de/how_many.voc
ovos_skill_iss_location/locale/de-de/iss.voc
ovos_skill_iss_location/locale/de-de/location.current.dialog
ovos_skill_iss_location/locale/de-de/location.unknown.dialog
ovos_skill_iss_location/ovos_skill_iss_location.egg-info/PKG-INFO
ovos_skill_iss_location/ovos_skill_iss_location.egg-info/SOURCES.txt
ovos_skill_iss_location/ovos_skill_iss_location.egg-info/dependency_links.txt
ovos_skill_iss_location/ovos_skill_iss_location.egg-info/entry_points.txt
ovos_skill_iss_location/ovos_skill_iss_location.egg-info/requires.txt
ovos_skill_iss_location/ovos_skill_iss_location.egg-info/top_level.txt
ovos_skill_iss_location-0.2.16.dist-info/LICENSE
ovos_skill_iss_location-0.2.16.dist-info/METADATA
ovos_skill_iss_location-0.2.16.dist-info/WHEEL
ovos_skill_iss_location-0.2.16.dist-info/entry_points.txt
ovos_skill_iss_location-0.2.16.dist-info/top_level.txt
ovos_skill_iss_location-0.2.16.dist-info/RECORD
