Metadata-Version: 2.1
Name: ovos-skill-iss-location
Version: 0.2.16
Summary: info about where is the space station and astronauts on board
Home-page: https://github.com/OpenVoiceOS/ovos-skill-iss-location
Author: OpenVoiceOS
Author-email: jarbasai@mailfence.com
License: Apache2.0
Keywords: ovos skill plugin
License-File: LICENSE
Requires-Dist: requests
Requires-Dist: skyfield
Requires-Dist: ovos-date-parser<1.0.0,>=0.0.3
Requires-Dist: ovos-workshop<8.0.0,>=0.0.12
Requires-Dist: ovos-bus-client>=1.0.1
Provides-Extra: gui
Requires-Dist: matplotlib; extra == "gui"
Requires-Dist: basemap; extra == "gui"
Requires-Dist: pillow; extra == "gui"
